asciibanner/__init__.py
asciibanner/asciibanner.py
asciibanner-1.7.dist-info/LICENCE.txt
asciibanner-1.7.dist-info/METADATA
asciibanner-1.7.dist-info/WHEEL
asciibanner-1.7.dist-info/top_level.txt
asciibanner-1.7.dist-info/RECORD
