Metadata-Version: 2.1
Name: asciibanner
Version: 1.7
Summary: AsciiBanner is a python script that allow you to do ASCII-Art with symbols
Home-page: https://root-me.org
Author: Dicashsin
Author-email: dicahsin@proton.me
License: MIT
Platform: UNKNOWN
Classifier: Development Status :: 4 - Beta
Classifier: License :: OSI Approved :: MIT License
Classifier: Operating System :: OS Independent
Classifier: Programming Language :: Python :: 3
Classifier: Environment :: Console
Classifier: Natural Language :: English
Requires-Dist: Pillow
Requires-Dist: numpy
